asyncgrpc/__init__.py
asyncgrpc/_channel.py
asyncgrpc/_protocol.py
asyncgrpc/_server.py
asyncgrpc-0.0.1.dist-info/METADATA
asyncgrpc-0.0.1.dist-info/RECORD
asyncgrpc-0.0.1.dist-info/WHEEL
asyncgrpc-0.0.1.dist-info/top_level.txt
