Metadata-Version: 2.1
Name: asyncgrpc
Version: 0.0.1
Summary: A gRPC implement using Python 3 asyncio
Home-page: https://github.com/tsangpozheng/asyncgrpc
Author: tsangpo
Author-email: tsangpozheng@gmail.com
License: UNKNOWN
Platform: UNKNOWN
Classifier: Programming Language :: Python :: 3
Classifier: License :: OSI Approved :: MIT License
Classifier: Operating System :: OS Independent
